docker_playbook/__init__.py
docker_playbook-0.0.1.dist-info/LICENSE-APACHE
docker_playbook-0.0.1.dist-info/LICENSE-MIT
docker_playbook-0.0.1.dist-info/METADATA
docker_playbook-0.0.1.dist-info/WHEEL
docker_playbook-0.0.1.dist-info/top_level.txt
docker_playbook-0.0.1.dist-info/RECORD
