Metadata-Version: 2.1
Name: docker-playbook
Version: 0.0.1
Summary: YAML driven docker playbook
Home-page: UNKNOWN
Author: Alex Yang
Author-email: aleozlx@gmail.com
License: UNKNOWN
Platform: UNKNOWN
Classifier: Programming Language :: Python :: 3
Classifier: Environment :: Console
Classifier: License :: OSI Approved :: Apache Software License
Classifier: License :: OSI Approved :: MIT License
